.bowerrc
.coveragerc
CHANGES.rst
LICENSE.txt
MANIFEST.in
README.rst
bower.json
compilecss.sh
development.ini
i18n.sh
requirements.txt
rtd.txt
setup.cfg
setup.py
kotti_bootswatch/__init__.py
kotti_bootswatch/fanstatic.py
kotti_bootswatch.egg-info/PKG-INFO
kotti_bootswatch.egg-info/SOURCES.txt
kotti_bootswatch.egg-info/dependency_links.txt
kotti_bootswatch.egg-info/entry_points.txt
kotti_bootswatch.egg-info/not-zip-safe
kotti_bootswatch.egg-info/requires.txt
kotti_bootswatch.egg-info/top_level.txt
kotti_bootswatch/scaffolds/__init__.py
kotti_bootswatch/scaffolds/scaffold/+dot+bowerrc
kotti_bootswatch/scaffolds/scaffold/+dot+gitignore_tmpl
kotti_bootswatch/scaffolds/scaffold/CHANGES.rst_tmpl
kotti_bootswatch/scaffolds/scaffold/LICENSE.txt_tmpl
kotti_bootswatch/scaffolds/scaffold/MANIFEST.in_tmpl
kotti_bootswatch/scaffolds/scaffold/README.maintainer.rst_tmpl
kotti_bootswatch/scaffolds/scaffold/README.rst_tmpl
kotti_bootswatch/scaffolds/scaffold/bower.json_tmpl
kotti_bootswatch/scaffolds/scaffold/build.less_tmpl
kotti_bootswatch/scaffolds/scaffold/compilecss.sh_tmpl
kotti_bootswatch/scaffolds/scaffold/development.ini_tmpl
kotti_bootswatch/scaffolds/scaffold/gen-from-base-theme.sh_tmpl
kotti_bootswatch/scaffolds/scaffold/quickstart.sh_tmpl
kotti_bootswatch/scaffolds/scaffold/requirements.txt
kotti_bootswatch/scaffolds/scaffold/setup.cfg_tmpl
kotti_bootswatch/scaffolds/scaffold/setup.py_tmpl
kotti_bootswatch/scaffolds/scaffold/+package+/__init__.py_tmpl
kotti_bootswatch/scaffolds/scaffold/+package+/fanstatic.py_tmpl
kotti_bootswatch/scaffolds/scaffold/+package+/static/kotti/base.less
kotti_bootswatch/scaffolds/scaffold/+package+/static/kotti/edit.less
kotti_bootswatch/scaffolds/scaffold/+package+/static/kotti/upload.less
kotti_bootswatch/scaffolds/scaffold/+package+/static/kotti/view.less
kotti_bootswatch/static/bootswatch/.bower.json
kotti_bootswatch/static/bootswatch/LICENSE
kotti_bootswatch/static/bootswatch/README.md
kotti_bootswatch/static/bootswatch/bower.json
kotti_bootswatch/static/bootswatch/amelia/bootstrap.css
kotti_bootswatch/static/bootswatch/amelia/bootstrap.min.css
kotti_bootswatch/static/bootswatch/amelia/bootswatch.less
kotti_bootswatch/static/bootswatch/amelia/variables.less
