Metadata-Version: 1.1
Name: kotti-bootswatch
Version: 0.1.2
Summary: Kotti bootswatch theme / theme generator
Home-page: https://github.com/mete0r/kotti_bootswatch
Author: mete0r
Author-email: kotti@googlegroups.com
License: BSD-derived (http://www.repoze.org/LICENSE.txt)
Keywords: kotti web cms wcms pylons pyramid sqlalchemy bootstrap
Platform: UNKNOWN
Classifier: Programming Language :: Python
Classifier: Programming Language :: Python :: 2.6
Classifier: Programming Language :: Python :: 2.7
Classifier: Framework :: Pylons
Classifier: Topic :: Internet :: WWW/HTTP
Classifier: Topic :: Internet :: WWW/HTTP :: Dynamic Content
Classifier: Topic :: Internet :: WWW/HTTP :: WSGI :: Application
Classifier: License :: Repoze Public License
